{
  "en":[
    {"Type":"number","Lvl":[{"lvlJc":"left","suff":"tab","numFmt":{"val":"upperRoman"},"lvlText":"Article %1.","pPr":{"ind":{"left":0,"firstLine":0},"bFromDocument":true,"type":"paraPr"}},{"lvlJc":"left","suff":"tab","numFmt":{"val":"decimalZero"},"lvlText":"Section %1.%2","pPr":{"ind":{"left":0,"firstLine":0},"bFromDocument":true,"type":"paraPr"}},{"lvlJc":"left","suff":"tab","numFmt":{"val":"lowerLetter"},"lvlText":"(%3)","pPr":{"ind":{"left":720,"firstLine":-432},"bFromDocument":true,"type":"paraPr"}},{"lvlJc":"right","suff":"tab","numFmt":{"val":"lowerRoman"},"lvlText":"(%4)","pPr":{"ind":{"left":864,"firstLine":-144},"bFromDocument":true,"type":"paraPr"}},{"lvlJc":"left","suff":"tab","numFmt":{"val":"decimal"},"lvlText":"%5)","pPr":{"ind":{"left":1008,"firstLine":-432},"bFromDocument":true,"type":"paraPr"}},{"lvlJc":"left","suff":"tab","numFmt":{"val":"lowerLetter"},"lvlText":"%6)","pPr":{"ind":{"left":1152,"firstLine":-432},"bFromDocument":true,"type":"paraPr"}},{"lvlJc":"right","suff":"tab","numFmt":{"val":"lowerRoman"},"lvlText":"%7)","pPr":{"ind":{"left":1296,"firstLine":-288},"bFromDocument":true,"type":"paraPr"}},{"lvlJc":"left","suff":"tab","numFmt":{"val":"lowerLetter"},"lvlText":"%8.","pPr":{"ind":{"left":1440,"firstLine":-432},"bFromDocument":true,"type":"paraPr"}},{"lvlJc":"right","suff":"tab","numFmt":{"val":"lowerRoman"},"lvlText":"%9.","pPr":{"ind":{"left":1584,"firstLine":-144},"bFromDocument":true,"type":"paraPr"}}],"Headings":true},
    {"Type":"hybrid","Lvl":[{"lvlJc":"left","suff":"space","numFmt":{"val":"decimal"},"lvlText":"Chapter %1","pPr":{"ind":{"left":0,"firstLine":0},"bFromDocument":true,"type":"paraPr"}},{"lvlJc":"left","suff":"nothing","numFmt":{"val":"none"},"lvlText":"","pPr":{"ind":{"left":0,"firstLine":0},"bFromDocument":true,"type":"paraPr"}},{"lvlJc":"left","suff":"nothing","numFmt":{"val":"none"},"lvlText":"","pPr":{"ind":{"left":0,"firstLine":0},"bFromDocument":true,"type":"paraPr"}},{"lvlJc":"left","suff":"nothing","numFmt":{"val":"none"},"lvlText":"","pPr":{"ind":{"left":0,"firstLine":0},"bFromDocument":true,"type":"paraPr"}},{"lvlJc":"left","suff":"nothing","numFmt":{"val":"none"},"lvlText":"","pPr":{"ind":{"left":0,"firstLine":0},"bFromDocument":true,"type":"paraPr"}},{"lvlJc":"left","suff":"nothing","numFmt":{"val":"none"},"lvlText":"","pPr":{"ind":{"left":0,"firstLine":0},"bFromDocument":true,"type":"paraPr"}},{"lvlJc":"left","suff":"nothing","numFmt":{"val":"none"},"lvlText":"","pPr":{"ind":{"left":0,"firstLine":0},"bFromDocument":true,"type":"paraPr"}},{"lvlJc":"left","suff":"nothing","numFmt":{"val":"none"},"lvlText":"","pPr":{"ind":{"left":0,"firstLine":0},"bFromDocument":true,"type":"paraPr"}},{"lvlJc":"left","suff":"nothing","numFmt":{"val":"none"},"lvlText":"","pPr":{"ind":{"left":0,"firstLine":0},"bFromDocument":true,"type":"paraPr"}}],"Headings":true}
  ],
  "ru":[
  {"Type":"number","Lvl":[{"lvlJc":"left","suff":"tab","numFmt":{"val":"upperRoman"},"lvlText":"Статья %1.","pPr":{"ind":{"left":709,"firstLine":0},"bFromDocument":true,"type":"paraPr"}},{"lvlJc":"left","suff":"tab","numFmt":{"val":"decimalZero"},"lvlText":"Раздел %1.%2","pPr":{"ind":{"left":709,"firstLine":0},"bFromDocument":true,"type":"paraPr"}},{"lvlJc":"left","suff":"tab","numFmt":{"val":"lowerLetter"},"lvlText":"(%3)","pPr":{"ind":{"left":1429,"firstLine":-432},"bFromDocument":true,"type":"paraPr"}},{"lvlJc":"right","suff":"tab","numFmt":{"val":"lowerRoman"},"lvlText":"(%4)","pPr":{"ind":{"left":1573,"firstLine":-144},"bFromDocument":true,"type":"paraPr"}},{"lvlJc":"left","suff":"tab","numFmt":{"val":"decimal"},"lvlText":"%5)","pPr":{"ind":{"left":1717,"firstLine":-432},"bFromDocument":true,"type":"paraPr"}},{"lvlJc":"left","suff":"tab","numFmt":{"val":"lowerLetter"},"lvlText":"%6)","pPr":{"ind":{"left":1861,"firstLine":-432},"bFromDocument":true,"type":"paraPr"}},{"lvlJc":"right","suff":"tab","numFmt":{"val":"lowerRoman"},"lvlText":"%7)","pPr":{"ind":{"left":2005,"firstLine":-288},"bFromDocument":true,"type":"paraPr"}},{"lvlJc":"left","suff":"tab","numFmt":{"val":"lowerLetter"},"lvlText":"%8.","pPr":{"ind":{"left":2149,"firstLine":-432},"bFromDocument":true,"type":"paraPr"}},{"lvlJc":"right","suff":"tab","numFmt":{"val":"lowerRoman"},"lvlText":"%9.","pPr":{"ind":{"left":2293,"firstLine":-144},"bFromDocument":true,"type":"paraPr"}}],"Headings":true},
  {"Type":"hybrid","Lvl":[{"lvlJc":"left","suff":"space","numFmt":{"val":"decimal"},"lvlText":"Глава %1","pPr":{"ind":{"left":0,"firstLine":0},"bFromDocument":true,"type":"paraPr"}},{"lvlJc":"left","suff":"nothing","numFmt":{"val":"none"},"lvlText":"","pPr":{"ind":{"left":0,"firstLine":0},"bFromDocument":true,"type":"paraPr"}},{"lvlJc":"left","suff":"nothing","numFmt":{"val":"none"},"lvlText":"","pPr":{"ind":{"left":0,"firstLine":0},"bFromDocument":true,"type":"paraPr"}},{"lvlJc":"left","suff":"nothing","numFmt":{"val":"none"},"lvlText":"","pPr":{"ind":{"left":0,"firstLine":0},"bFromDocument":true,"type":"paraPr"}},{"lvlJc":"left","suff":"nothing","numFmt":{"val":"none"},"lvlText":"","pPr":{"ind":{"left":0,"firstLine":0},"bFromDocument":true,"type":"paraPr"}},{"lvlJc":"left","suff":"nothing","numFmt":{"val":"none"},"lvlText":"","pPr":{"ind":{"left":0,"firstLine":0},"bFromDocument":true,"type":"paraPr"}},{"lvlJc":"left","suff":"nothing","numFmt":{"val":"none"},"lvlText":"","pPr":{"ind":{"left":0,"firstLine":0},"bFromDocument":true,"type":"paraPr"}},{"lvlJc":"left","suff":"nothing","numFmt":{"val":"none"},"lvlText":"","pPr":{"ind":{"left":0,"firstLine":0},"bFromDocument":true,"type":"paraPr"}},{"lvlJc":"left","suff":"nothing","numFmt":{"val":"none"},"lvlText":"","pPr":{"ind":{"left":0,"firstLine":0},"bFromDocument":true,"type":"paraPr"}}],"Headings":true}
  ],
  "de":[
  {"Type":"number","Lvl":[{"lvlJc":"left","suff":"tab","numFmt":{"val":"upperRoman"},"lvlText":"Artikel %1.","pPr":{"ind":{"left":0,"firstLine":0},"bFromDocument":true,"type":"paraPr"}},{"lvlJc":"left","suff":"tab","numFmt":{"val":"decimalZero"},"lvlText":"Abschnitt %1.%2","pPr":{"ind":{"left":0,"firstLine":0},"bFromDocument":true,"type":"paraPr"}},{"lvlJc":"left","suff":"tab","numFmt":{"val":"lowerLetter"},"lvlText":"(%3)","pPr":{"ind":{"left":720,"firstLine":-432},"bFromDocument":true,"type":"paraPr"}},{"lvlJc":"right","suff":"tab","numFmt":{"val":"lowerRoman"},"lvlText":"(%4)","pPr":{"ind":{"left":864,"firstLine":-144},"bFromDocument":true,"type":"paraPr"}},{"lvlJc":"left","suff":"tab","numFmt":{"val":"decimal"},"lvlText":"%5)","pPr":{"ind":{"left":1008,"firstLine":-432},"bFromDocument":true,"type":"paraPr"}},{"lvlJc":"left","suff":"tab","numFmt":{"val":"lowerLetter"},"lvlText":"%6)","pPr":{"ind":{"left":1152,"firstLine":-432},"bFromDocument":true,"type":"paraPr"}},{"lvlJc":"right","suff":"tab","numFmt":{"val":"lowerRoman"},"lvlText":"%7)","pPr":{"ind":{"left":1296,"firstLine":-288},"bFromDocument":true,"type":"paraPr"}},{"lvlJc":"left","suff":"tab","numFmt":{"val":"lowerLetter"},"lvlText":"%8.","pPr":{"ind":{"left":1440,"firstLine":-432},"bFromDocument":true,"type":"paraPr"}},{"lvlJc":"right","suff":"tab","numFmt":{"val":"lowerRoman"},"lvlText":"%9.","pPr":{"ind":{"left":1584,"firstLine":-144},"bFromDocument":true,"type":"paraPr"}}],"Headings":true},
  {"Type":"hybrid","Lvl":[{"lvlJc":"left","suff":"space","numFmt":{"val":"decimal"},"lvlText":"Kapitel %1","pPr":{"ind":{"left":0,"firstLine":0},"bFromDocument":true,"type":"paraPr"}},{"lvlJc":"left","suff":"nothing","numFmt":{"val":"none"},"lvlText":"","pPr":{"ind":{"left":0,"firstLine":0},"bFromDocument":true,"type":"paraPr"}},{"lvlJc":"left","suff":"nothing","numFmt":{"val":"none"},"lvlText":"","pPr":{"ind":{"left":0,"firstLine":0},"bFromDocument":true,"type":"paraPr"}},{"lvlJc":"left","suff":"nothing","numFmt":{"val":"none"},"lvlText":"","pPr":{"ind":{"left":0,"firstLine":0},"bFromDocument":true,"type":"paraPr"}},{"lvlJc":"left","suff":"nothing","numFmt":{"val":"none"},"lvlText":"","pPr":{"ind":{"left":0,"firstLine":0},"bFromDocument":true,"type":"paraPr"}},{"lvlJc":"left","suff":"nothing","numFmt":{"val":"none"},"lvlText":"","pPr":{"ind":{"left":0,"firstLine":0},"bFromDocument":true,"type":"paraPr"}},{"lvlJc":"left","suff":"nothing","numFmt":{"val":"none"},"lvlText":"","pPr":{"ind":{"left":0,"firstLine":0},"bFromDocument":true,"type":"paraPr"}},{"lvlJc":"left","suff":"nothing","numFmt":{"val":"none"},"lvlText":"","pPr":{"ind":{"left":0,"firstLine":0},"bFromDocument":true,"type":"paraPr"}},{"lvlJc":"left","suff":"nothing","numFmt":{"val":"none"},"lvlText":"","pPr":{"ind":{"left":0,"firstLine":0},"bFromDocument":true,"type":"paraPr"}}],"Headings":true}
  ],
  "fr":[
  {"Type":"number","Lvl":[{"lvlJc":"left","suff":"tab","numFmt":{"val":"upperRoman"},"lvlText":"Article %1.","pPr":{"ind":{"left":0,"firstLine":0},"bFromDocument":true,"type":"paraPr"}},{"lvlJc":"left","suff":"tab","numFmt":{"val":"decimalZero"},"lvlText":"Section %1.%2","pPr":{"ind":{"left":0,"firstLine":0},"bFromDocument":true,"type":"paraPr"}},{"lvlJc":"left","suff":"tab","numFmt":{"val":"lowerLetter"},"lvlText":"(%3)","pPr":{"ind":{"left":720,"firstLine":-432},"bFromDocument":true,"type":"paraPr"}},{"lvlJc":"right","suff":"tab","numFmt":{"val":"lowerRoman"},"lvlText":"(%4)","pPr":{"ind":{"left":864,"firstLine":-144},"bFromDocument":true,"type":"paraPr"}},{"lvlJc":"left","suff":"tab","numFmt":{"val":"decimal"},"lvlText":"%5)","pPr":{"ind":{"left":1008,"firstLine":-432},"bFromDocument":true,"type":"paraPr"}},{"lvlJc":"left","suff":"tab","numFmt":{"val":"lowerLetter"},"lvlText":"%6)","pPr":{"ind":{"left":1152,"firstLine":-432},"bFromDocument":true,"type":"paraPr"}},{"lvlJc":"right","suff":"tab","numFmt":{"val":"lowerRoman"},"lvlText":"%7)","pPr":{"ind":{"left":1296,"firstLine":-288},"bFromDocument":true,"type":"paraPr"}},{"lvlJc":"left","suff":"tab","numFmt":{"val":"lowerLetter"},"lvlText":"%8.","pPr":{"ind":{"left":1440,"firstLine":-432},"bFromDocument":true,"type":"paraPr"}},{"lvlJc":"right","suff":"tab","numFmt":{"val":"lowerRoman"},"lvlText":"%9.","pPr":{"ind":{"left":1584,"firstLine":-144},"bFromDocument":true,"type":"paraPr"}}],"Headings":true},
  {"Type":"hybrid","Lvl":[{"lvlJc":"left","suff":"space","numFmt":{"val":"decimal"},"lvlText":"Chapitre %1","pPr":{"ind":{"left":0,"firstLine":0},"bFromDocument":true,"type":"paraPr"}},{"lvlJc":"left","suff":"nothing","numFmt":{"val":"none"},"lvlText":"","pPr":{"ind":{"left":0,"firstLine":0},"bFromDocument":true,"type":"paraPr"}},{"lvlJc":"left","suff":"nothing","numFmt":{"val":"none"},"lvlText":"","pPr":{"ind":{"left":0,"firstLine":0},"bFromDocument":true,"type":"paraPr"}},{"lvlJc":"left","suff":"nothing","numFmt":{"val":"none"},"lvlText":"","pPr":{"ind":{"left":0,"firstLine":0},"bFromDocument":true,"type":"paraPr"}},{"lvlJc":"left","suff":"nothing","numFmt":{"val":"none"},"lvlText":"","pPr":{"ind":{"left":0,"firstLine":0},"bFromDocument":true,"type":"paraPr"}},{"lvlJc":"left","suff":"nothing","numFmt":{"val":"none"},"lvlText":"","pPr":{"ind":{"left":0,"firstLine":0},"bFromDocument":true,"type":"paraPr"}},{"lvlJc":"left","suff":"nothing","numFmt":{"val":"none"},"lvlText":"","pPr":{"ind":{"left":0,"firstLine":0},"bFromDocument":true,"type":"paraPr"}},{"lvlJc":"left","suff":"nothing","numFmt":{"val":"none"},"lvlText":"","pPr":{"ind":{"left":0,"firstLine":0},"bFromDocument":true,"type":"paraPr"}},{"lvlJc":"left","suff":"nothing","numFmt":{"val":"none"},"lvlText":"","pPr":{"ind":{"left":0,"firstLine":0},"bFromDocument":true,"type":"paraPr"}}],"Headings":true}
  ],
  "es":[
  {"Type":"number","Lvl":[{"lvlJc":"left","suff":"tab","numFmt":{"val":"upperRoman"},"lvlText":"Artículo %1.","pPr":{"ind":{"left":0,"firstLine":0},"bFromDocument":true,"type":"paraPr"}},{"lvlJc":"left","suff":"tab","numFmt":{"val":"decimalZero"},"lvlText":"Sección %1.%2","pPr":{"ind":{"left":0,"firstLine":0},"bFromDocument":true,"type":"paraPr"}},{"lvlJc":"left","suff":"tab","numFmt":{"val":"lowerLetter"},"lvlText":"(%3)","pPr":{"ind":{"left":720,"firstLine":-432},"bFromDocument":true,"type":"paraPr"}},{"lvlJc":"right","suff":"tab","numFmt":{"val":"lowerRoman"},"lvlText":"(%4)","pPr":{"ind":{"left":864,"firstLine":-144},"bFromDocument":true,"type":"paraPr"}},{"lvlJc":"left","suff":"tab","numFmt":{"val":"decimal"},"lvlText":"%5)","pPr":{"ind":{"left":1008,"firstLine":-432},"bFromDocument":true,"type":"paraPr"}},{"lvlJc":"left","suff":"tab","numFmt":{"val":"lowerLetter"},"lvlText":"%6)","pPr":{"ind":{"left":1152,"firstLine":-432},"bFromDocument":true,"type":"paraPr"}},{"lvlJc":"right","suff":"tab","numFmt":{"val":"lowerRoman"},"lvlText":"%7)","pPr":{"ind":{"left":1296,"firstLine":-288},"bFromDocument":true,"type":"paraPr"}},{"lvlJc":"left","suff":"tab","numFmt":{"val":"lowerLetter"},"lvlText":"%8.","pPr":{"ind":{"left":1440,"firstLine":-432},"bFromDocument":true,"type":"paraPr"}},{"lvlJc":"right","suff":"tab","numFmt":{"val":"lowerRoman"},"lvlText":"%9.","pPr":{"ind":{"left":1584,"firstLine":-144},"bFromDocument":true,"type":"paraPr"}}],"Headings":true},
  {"Type":"hybrid","Lvl":[{"lvlJc":"left","suff":"space","numFmt":{"val":"decimal"},"lvlText":"Capítulo %1","pPr":{"ind":{"left":0,"firstLine":0},"bFromDocument":true,"type":"paraPr"}},{"lvlJc":"left","suff":"nothing","numFmt":{"val":"none"},"lvlText":"","pPr":{"ind":{"left":0,"firstLine":0},"bFromDocument":true,"type":"paraPr"}},{"lvlJc":"left","suff":"nothing","numFmt":{"val":"none"},"lvlText":"","pPr":{"ind":{"left":0,"firstLine":0},"bFromDocument":true,"type":"paraPr"}},{"lvlJc":"left","suff":"nothing","numFmt":{"val":"none"},"lvlText":"","pPr":{"ind":{"left":0,"firstLine":0},"bFromDocument":true,"type":"paraPr"}},{"lvlJc":"left","suff":"nothing","numFmt":{"val":"none"},"lvlText":"","pPr":{"ind":{"left":0,"firstLine":0},"bFromDocument":true,"type":"paraPr"}},{"lvlJc":"left","suff":"nothing","numFmt":{"val":"none"},"lvlText":"","pPr":{"ind":{"left":0,"firstLine":0},"bFromDocument":true,"type":"paraPr"}},{"lvlJc":"left","suff":"nothing","numFmt":{"val":"none"},"lvlText":"","pPr":{"ind":{"left":0,"firstLine":0},"bFromDocument":true,"type":"paraPr"}},{"lvlJc":"left","suff":"nothing","numFmt":{"val":"none"},"lvlText":"","pPr":{"ind":{"left":0,"firstLine":0},"bFromDocument":true,"type":"paraPr"}},{"lvlJc":"left","suff":"nothing","numFmt":{"val":"none"},"lvlText":"","pPr":{"ind":{"left":0,"firstLine":0},"bFromDocument":true,"type":"paraPr"}}],"Headings":true}
  ],
  "it":[
  {"Type":"number","Lvl":[{"lvlJc":"left","suff":"tab","numFmt":{"val":"upperRoman"},"lvlText":"Articolo %1.","pPr":{"ind":{"left":0,"firstLine":0},"bFromDocument":true,"type":"paraPr"}},{"lvlJc":"left","suff":"tab","numFmt":{"val":"decimalZero"},"lvlText":"Sezione %1.%2","pPr":{"ind":{"left":0,"firstLine":0},"bFromDocument":true,"type":"paraPr"}},{"lvlJc":"left","suff":"tab","numFmt":{"val":"lowerLetter"},"lvlText":"(%3)","pPr":{"ind":{"left":720,"firstLine":-432},"bFromDocument":true,"type":"paraPr"}},{"lvlJc":"right","suff":"tab","numFmt":{"val":"lowerRoman"},"lvlText":"(%4)","pPr":{"ind":{"left":864,"firstLine":-144},"bFromDocument":true,"type":"paraPr"}},{"lvlJc":"left","suff":"tab","numFmt":{"val":"decimal"},"lvlText":"%5)","pPr":{"ind":{"left":1008,"firstLine":-432},"bFromDocument":true,"type":"paraPr"}},{"lvlJc":"left","suff":"tab","numFmt":{"val":"lowerLetter"},"lvlText":"%6)","pPr":{"ind":{"left":1152,"firstLine":-432},"bFromDocument":true,"type":"paraPr"}},{"lvlJc":"right","suff":"tab","numFmt":{"val":"lowerRoman"},"lvlText":"%7)","pPr":{"ind":{"left":1296,"firstLine":-288},"bFromDocument":true,"type":"paraPr"}},{"lvlJc":"left","suff":"tab","numFmt":{"val":"lowerLetter"},"lvlText":"%8.","pPr":{"ind":{"left":1440,"firstLine":-432},"bFromDocument":true,"type":"paraPr"}},{"lvlJc":"right","suff":"tab","numFmt":{"val":"lowerRoman"},"lvlText":"%9.","pPr":{"ind":{"left":1584,"firstLine":-144},"bFromDocument":true,"type":"paraPr"}}],"Headings":true},
  {"Type":"hybrid","Lvl":[{"lvlJc":"left","suff":"space","numFmt":{"val":"decimal"},"lvlText":"Capitolo %1","pPr":{"ind":{"left":0,"firstLine":0},"bFromDocument":true,"type":"paraPr"}},{"lvlJc":"left","suff":"nothing","numFmt":{"val":"none"},"lvlText":"","pPr":{"ind":{"left":0,"firstLine":0},"bFromDocument":true,"type":"paraPr"}},{"lvlJc":"left","suff":"nothing","numFmt":{"val":"none"},"lvlText":"","pPr":{"ind":{"left":0,"firstLine":0},"bFromDocument":true,"type":"paraPr"}},{"lvlJc":"left","suff":"nothing","numFmt":{"val":"none"},"lvlText":"","pPr":{"ind":{"left":0,"firstLine":0},"bFromDocument":true,"type":"paraPr"}},{"lvlJc":"left","suff":"nothing","numFmt":{"val":"none"},"lvlText":"","pPr":{"ind":{"left":0,"firstLine":0},"bFromDocument":true,"type":"paraPr"}},{"lvlJc":"left","suff":"nothing","numFmt":{"val":"none"},"lvlText":"","pPr":{"ind":{"left":0,"firstLine":0},"bFromDocument":true,"type":"paraPr"}},{"lvlJc":"left","suff":"nothing","numFmt":{"val":"none"},"lvlText":"","pPr":{"ind":{"left":0,"firstLine":0},"bFromDocument":true,"type":"paraPr"}},{"lvlJc":"left","suff":"nothing","numFmt":{"val":"none"},"lvlText":"","pPr":{"ind":{"left":0,"firstLine":0},"bFromDocument":true,"type":"paraPr"}},{"lvlJc":"left","suff":"nothing","numFmt":{"val":"none"},"lvlText":"","pPr":{"ind":{"left":0,"firstLine":0},"bFromDocument":true,"type":"paraPr"}}],"Headings":true}
  ],
  "zh":[
  {"Type":"number","Lvl":[{"lvlJc":"left","suff":"tab","numFmt":{"val":"upperRoman"},"lvlText":"第 %1.章","pPr":{"ind":{"left":0,"firstLine":0},"bFromDocument":true,"type":"paraPr"}},{"lvlJc":"left","suff":"tab","numFmt":{"val":"decimalZero"},"lvlText":"第 %1.%2節","pPr":{"ind":{"left":0,"firstLine":0},"bFromDocument":true,"type":"paraPr"}},{"lvlJc":"left","suff":"tab","numFmt":{"val":"lowerLetter"},"lvlText":"(%3)","pPr":{"ind":{"left":720,"firstLine":-432},"bFromDocument":true,"type":"paraPr"}},{"lvlJc":"right","suff":"tab","numFmt":{"val":"lowerRoman"},"lvlText":"(%4)","pPr":{"ind":{"left":864,"firstLine":-144},"bFromDocument":true,"type":"paraPr"}},{"lvlJc":"left","suff":"tab","numFmt":{"val":"decimal"},"lvlText":"%5)","pPr":{"ind":{"left":1008,"firstLine":-432},"bFromDocument":true,"type":"paraPr"}},{"lvlJc":"left","suff":"tab","numFmt":{"val":"lowerLetter"},"lvlText":"%6)","pPr":{"ind":{"left":1152,"firstLine":-432},"bFromDocument":true,"type":"paraPr"}},{"lvlJc":"right","suff":"tab","numFmt":{"val":"lowerRoman"},"lvlText":"%7)","pPr":{"ind":{"left":1296,"firstLine":-288},"bFromDocument":true,"type":"paraPr"}},{"lvlJc":"left","suff":"tab","numFmt":{"val":"lowerLetter"},"lvlText":"%8.","pPr":{"ind":{"left":1440,"firstLine":-432},"bFromDocument":true,"type":"paraPr"}},{"lvlJc":"right","suff":"tab","numFmt":{"val":"lowerRoman"},"lvlText":"%9.","pPr":{"ind":{"left":1584,"firstLine":-144},"bFromDocument":true,"type":"paraPr"}}],"Headings":true},
  {"Type":"hybrid","Lvl":[{"lvlJc":"left","suff":"space","numFmt":{"val":"decimal"},"lvlText":"第 %1項","pPr":{"ind":{"left":0,"firstLine":0},"bFromDocument":true,"type":"paraPr"}},{"lvlJc":"left","suff":"nothing","numFmt":{"val":"none"},"lvlText":"","pPr":{"ind":{"left":0,"firstLine":0},"bFromDocument":true,"type":"paraPr"}},{"lvlJc":"left","suff":"nothing","numFmt":{"val":"none"},"lvlText":"","pPr":{"ind":{"left":0,"firstLine":0},"bFromDocument":true,"type":"paraPr"}},{"lvlJc":"left","suff":"nothing","numFmt":{"val":"none"},"lvlText":"","pPr":{"ind":{"left":0,"firstLine":0},"bFromDocument":true,"type":"paraPr"}},{"lvlJc":"left","suff":"nothing","numFmt":{"val":"none"},"lvlText":"","pPr":{"ind":{"left":0,"firstLine":0},"bFromDocument":true,"type":"paraPr"}},{"lvlJc":"left","suff":"nothing","numFmt":{"val":"none"},"lvlText":"","pPr":{"ind":{"left":0,"firstLine":0},"bFromDocument":true,"type":"paraPr"}},{"lvlJc":"left","suff":"nothing","numFmt":{"val":"none"},"lvlText":"","pPr":{"ind":{"left":0,"firstLine":0},"bFromDocument":true,"type":"paraPr"}},{"lvlJc":"left","suff":"nothing","numFmt":{"val":"none"},"lvlText":"","pPr":{"ind":{"left":0,"firstLine":0},"bFromDocument":true,"type":"paraPr"}},{"lvlJc":"left","suff":"nothing","numFmt":{"val":"none"},"lvlText":"","pPr":{"ind":{"left":0,"firstLine":0},"bFromDocument":true,"type":"paraPr"}}],"Headings":true}
  ]
}